{
  "60,-40": {
    "SourceVersionHash": "3ssxTk9I94yjvXbK+9Lhsm1b21k=",
    "VersionHash": "rEZ2fTASmOCBw6yzUmHCywv8QGY="
  },
  "62,-40": {
    "SourceVersionHash": "3ssxTk9I94yjvXbK+9Lhsm1b21k=",
    "VersionHash": "rEZ2fTASmOCBw6yzUmHCywv8QGY="
  },
  "60,-39": {
    "SourceVersionHash": "3ssxTk9I94yjvXbK+9Lhsm1b21k=",
    "VersionHash": "rEZ2fTASmOCBw6yzUmHCywv8QGY="
  },
  "61,-40": {
    "SourceVersionHash": "3ssxTk9I94yjvXbK+9Lhsm1b21k=",
    "VersionHash": "rEZ2fTASmOCBw6yzUmHCywv8QGY="
  },
  "61,-39": {
    "SourceVersionHash": "3ssxTk9I94yjvXbK+9Lhsm1b21k=",
    "VersionHash": "rEZ2fTASmOCBw6yzUmHCywv8QGY="
  },
  "62,-39": {
    "SourceVersionHash": "3ssxTk9I94yjvXbK+9Lhsm1b21k=",
    "VersionHash": "rEZ2fTASmOCBw6yzUmHCywv8QGY="
  },
  "60,-38": {
    "SourceVersionHash": "3ssxTk9I94yjvXbK+9Lhsm1b21k=",
    "VersionHash": "rEZ2fTASmOCBw6yzUmHCywv8QGY="
  },
  "61,-38": {
    "SourceVersionHash": "3ssxTk9I94yjvXbK+9Lhsm1b21k=",
    "VersionHash": "rEZ2fTASmOCBw6yzUmHCywv8QGY="
  },
  "62,-38": {
    "SourceVersionHash": "3ssxTk9I94yjvXbK+9Lhsm1b21k=",
    "VersionHash": "rEZ2fTASmOCBw6yzUmHCywv8QGY="
  },
  "61,-37": {
    "SourceVersionHash": "3ssxTk9I94yjvXbK+9Lhsm1b21k=",
    "VersionHash": "rEZ2fTASmOCBw6yzUmHCywv8QGY="
  },
  "62,-37": {
    "SourceVersionHash": "3ssxTk9I94yjvXbK+9Lhsm1b21k=",
    "VersionHash": "rEZ2fTASmOCBw6yzUmHCywv8QGY="
  },
  "60,-37": {
    "SourceVersionHash": "3ssxTk9I94yjvXbK+9Lhsm1b21k=",
    "VersionHash": "rEZ2fTASmOCBw6yzUmHCywv8QGY="
  },
  "60,-36": {
    "SourceVersionHash": "3ssxTk9I94yjvXbK+9Lhsm1b21k=",
    "VersionHash": "WEUAX3M3Bvm07z6Lhz3AuQElzJo="
  },
  "62,-36": {
    "SourceVersionHash": "3ssxTk9I94yjvXbK+9Lhsm1b21k=",
    "VersionHash": "WEUAX3M3Bvm07z6Lhz3AuQElzJo="
  },
  "61,-36": {
    "SourceVersionHash": "3ssxTk9I94yjvXbK+9Lhsm1b21k=",
    "VersionHash": "rEZ2fTASmOCBw6yzUmHCywv8QGY="
  },
  "61,-33": {
    "SourceVersionHash": "3ssxTk9I94yjvXbK+9Lhsm1b21k=",
    "VersionHash": "rEZ2fTASmOCBw6yzUmHCywv8QGY="
  },
  "60,-35": {
    "SourceVersionHash": "3ssxTk9I94yjvXbK+9Lhsm1b21k=",
    "VersionHash": "WEUAX3M3Bvm07z6Lhz3AuQElzJo="
  },
  "60,-33": {
    "SourceVersionHash": "3ssxTk9I94yjvXbK+9Lhsm1b21k=",
    "VersionHash": "rEZ2fTASmOCBw6yzUmHCywv8QGY="
  },
  "61,-35": {
    "SourceVersionHash": "3ssxTk9I94yjvXbK+9Lhsm1b21k=",
    "VersionHash": "WEUAX3M3Bvm07z6Lhz3AuQElzJo="
  },
  "62,-33": {
    "SourceVersionHash": "3ssxTk9I94yjvXbK+9Lhsm1b21k=",
    "VersionHash": "rEZ2fTASmOCBw6yzUmHCywv8QGY="
  },
  "62,-35": {
    "SourceVersionHash": "3ssxTk9I94yjvXbK+9Lhsm1b21k=",
    "VersionHash": "WEUAX3M3Bvm07z6Lhz3AuQElzJo="
  },
  "60,-32": {
    "SourceVersionHash": "/0XBUT5cCdQ1BsEjZ8zN+XrBOjA=",
    "VersionHash": "rEZ2fTASmOCBw6yzUmHCywv8QGY="
  },
  "60,-34": {
    "SourceVersionHash": "3ssxTk9I94yjvXbK+9Lhsm1b21k=",
    "VersionHash": "WEUAX3M3Bvm07z6Lhz3AuQElzJo="
  },
  "61,-34": {
    "SourceVersionHash": "3ssxTk9I94yjvXbK+9Lhsm1b21k=",
    "VersionHash": "WEUAX3M3Bvm07z6Lhz3AuQElzJo="
  },
  "61,-32": {
    "SourceVersionHash": "/0XBUT5cCdQ1BsEjZ8zN+XrBOjA=",
    "VersionHash": "rEZ2fTASmOCBw6yzUmHCywv8QGY="
  },
  "62,-32": {
    "SourceVersionHash": "/0XBUT5cCdQ1BsEjZ8zN+XrBOjA=",
    "VersionHash": "rEZ2fTASmOCBw6yzUmHCywv8QGY="
  },
  "62,-34": {
    "SourceVersionHash": "3ssxTk9I94yjvXbK+9Lhsm1b21k=",
    "VersionHash": "WEUAX3M3Bvm07z6Lhz3AuQElzJo="
  },
  "65,-31": {
    "SourceVersionHash": "oM9pNtQh72w3g6sBjbbIa1530qM=",
    "VersionHash": "eWSl78MbfdB7IaCo0zeLFWWMd4Y="
  },
  "66,-31": {
    "SourceVersionHash": "oM9pNtQh72w3g6sBjbbIa1530qM=",
    "VersionHash": "eWSl78MbfdB7IaCo0zeLFWWMd4Y="
  },
  "67,-31": {
    "SourceVersionHash": "oM9pNtQh72w3g6sBjbbIa1530qM=",
    "VersionHash": "eWSl78MbfdB7IaCo0zeLFWWMd4Y="
  },
  "69,-31": {
    "SourceVersionHash": "oM9pNtQh72w3g6sBjbbIa1530qM=",
    "VersionHash": "U1gFTuAs5xmtOODFSDH+EO8aezw="
  },
  "68,-31": {
    "SourceVersionHash": "oM9pNtQh72w3g6sBjbbIa1530qM=",
    "VersionHash": "U1gFTuAs5xmtOODFSDH+EO8aezw="
  },
  "60,-31": {
    "SourceVersionHash": "/0XBUT5cCdQ1BsEjZ8zN+XrBOjA=",
    "VersionHash": "rEZ2fTASmOCBw6yzUmHCywv8QGY="
  },
  "61,-31": {
    "SourceVersionHash": "/0XBUT5cCdQ1BsEjZ8zN+XrBOjA=",
    "VersionHash": "rEZ2fTASmOCBw6yzUmHCywv8QGY="
  },
  "62,-31": {
    "SourceVersionHash": "/0XBUT5cCdQ1BsEjZ8zN+XrBOjA=",
    "VersionHash": "rEZ2fTASmOCBw6yzUmHCywv8QGY="
  },
  "64,-31": {
    "SourceVersionHash": "oM9pNtQh72w3g6sBjbbIa1530qM=",
    "VersionHash": "cnrzB/AANEPFjP6edNYGnVd8R90="
  },
  "63,-31": {
    "SourceVersionHash": "/0XBUT5cCdQ1BsEjZ8zN+XrBOjA=",
    "VersionHash": "WEUAX3M3Bvm07z6Lhz3AuQElzJo="
  },
  "69,-36": {
    "SourceVersionHash": "o1yIP49yThqcdwiyziuGPD6ICOE=",
    "VersionHash": "lJKo50H+lCe+QbHNaxkDz1wEX0w="
  },
  "65,-38": {
    "SourceVersionHash": "o1yIP49yThqcdwiyziuGPD6ICOE=",
    "VersionHash": "lJKo50H+lCe+QbHNaxkDz1wEX0w="
  },
  "63,-38": {
    "SourceVersionHash": "3ssxTk9I94yjvXbK+9Lhsm1b21k=",
    "VersionHash": "rEZ2fTASmOCBw6yzUmHCywv8QGY="
  },
  "68,-32": {
    "SourceVersionHash": "oM9pNtQh72w3g6sBjbbIa1530qM=",
    "VersionHash": "GL03MpIkh8Knf8qccDmBO8SgewU="
  },
  "69,-37": {
    "SourceVersionHash": "o1yIP49yThqcdwiyziuGPD6ICOE=",
    "VersionHash": "lJKo50H+lCe+QbHNaxkDz1wEX0w="
  },
  "68,-38": {
    "SourceVersionHash": "o1yIP49yThqcdwiyziuGPD6ICOE=",
    "VersionHash": "lJKo50H+lCe+QbHNaxkDz1wEX0w="
  },
  "64,-32": {
    "SourceVersionHash": "oM9pNtQh72w3g6sBjbbIa1530qM=",
    "VersionHash": "GL03MpIkh8Knf8qccDmBO8SgewU="
  },
  "63,-36": {
    "SourceVersionHash": "3ssxTk9I94yjvXbK+9Lhsm1b21k=",
    "VersionHash": "rEZ2fTASmOCBw6yzUmHCywv8QGY="
  },
  "67,-36": {
    "SourceVersionHash": "o1yIP49yThqcdwiyziuGPD6ICOE=",
    "VersionHash": "lJKo50H+lCe+QbHNaxkDz1wEX0w="
  },
  "69,-38": {
    "SourceVersionHash": "o1yIP49yThqcdwiyziuGPD6ICOE=",
    "VersionHash": "lJKo50H+lCe+QbHNaxkDz1wEX0w="
  },
  "67,-37": {
    "SourceVersionHash": "o1yIP49yThqcdwiyziuGPD6ICOE=",
    "VersionHash": "lJKo50H+lCe+QbHNaxkDz1wEX0w="
  },
  "63,-35": {
    "SourceVersionHash": "3ssxTk9I94yjvXbK+9Lhsm1b21k=",
    "VersionHash": "rEZ2fTASmOCBw6yzUmHCywv8QGY="
  },
  "66,-35": {
    "SourceVersionHash": "o1yIP49yThqcdwiyziuGPD6ICOE=",
    "VersionHash": "lJKo50H+lCe+QbHNaxkDz1wEX0w="
  },
  "63,-34": {
    "SourceVersionHash": "3ssxTk9I94yjvXbK+9Lhsm1b21k=",
    "VersionHash": "rEZ2fTASmOCBw6yzUmHCywv8QGY="
  },
  "64,-37": {
    "SourceVersionHash": "o1yIP49yThqcdwiyziuGPD6ICOE=",
    "VersionHash": "rEZ2fTASmOCBw6yzUmHCywv8QGY="
  },
  "65,-35": {
    "SourceVersionHash": "o1yIP49yThqcdwiyziuGPD6ICOE=",
    "VersionHash": "lJKo50H+lCe+QbHNaxkDz1wEX0w="
  },
  "68,-40": {
    "SourceVersionHash": "o1yIP49yThqcdwiyziuGPD6ICOE=",
    "VersionHash": "viyHSlgBplXbs793wGh/zfYoRXA="
  },
  "69,-32": {
    "SourceVersionHash": "oM9pNtQh72w3g6sBjbbIa1530qM=",
    "VersionHash": "GL03MpIkh8Knf8qccDmBO8SgewU="
  },
  "69,-35": {
    "SourceVersionHash": "o1yIP49yThqcdwiyziuGPD6ICOE=",
    "VersionHash": "lJKo50H+lCe+QbHNaxkDz1wEX0w="
  },
  "67,-35": {
    "SourceVersionHash": "o1yIP49yThqcdwiyziuGPD6ICOE=",
    "VersionHash": "lJKo50H+lCe+QbHNaxkDz1wEX0w="
  },
  "66,-34": {
    "SourceVersionHash": "o1yIP49yThqcdwiyziuGPD6ICOE=",
    "VersionHash": "lJKo50H+lCe+QbHNaxkDz1wEX0w="
  },
  "69,-34": {
    "SourceVersionHash": "o1yIP49yThqcdwiyziuGPD6ICOE=",
    "VersionHash": "lJKo50H+lCe+QbHNaxkDz1wEX0w="
  },
  "67,-38": {
    "SourceVersionHash": "o1yIP49yThqcdwiyziuGPD6ICOE=",
    "VersionHash": "lJKo50H+lCe+QbHNaxkDz1wEX0w="
  },
  "67,-34": {
    "SourceVersionHash": "o1yIP49yThqcdwiyziuGPD6ICOE=",
    "VersionHash": "lJKo50H+lCe+QbHNaxkDz1wEX0w="
  },
  "63,-32": {
    "SourceVersionHash": "/0XBUT5cCdQ1BsEjZ8zN+XrBOjA=",
    "VersionHash": "rEZ2fTASmOCBw6yzUmHCywv8QGY="
  },
  "66,-36": {
    "SourceVersionHash": "o1yIP49yThqcdwiyziuGPD6ICOE=",
    "VersionHash": "lJKo50H+lCe+QbHNaxkDz1wEX0w="
  },
  "64,-33": {
    "SourceVersionHash": "o1yIP49yThqcdwiyziuGPD6ICOE=",
    "VersionHash": "rEZ2fTASmOCBw6yzUmHCywv8QGY="
  },
  "66,-38": {
    "SourceVersionHash": "o1yIP49yThqcdwiyziuGPD6ICOE=",
    "VersionHash": "lJKo50H+lCe+QbHNaxkDz1wEX0w="
  },
  "64,-34": {
    "SourceVersionHash": "o1yIP49yThqcdwiyziuGPD6ICOE=",
    "VersionHash": "rEZ2fTASmOCBw6yzUmHCywv8QGY="
  },
  "65,-32": {
    "SourceVersionHash": "oM9pNtQh72w3g6sBjbbIa1530qM=",
    "VersionHash": "GL03MpIkh8Knf8qccDmBO8SgewU="
  },
  "63,-37": {
    "SourceVersionHash": "3ssxTk9I94yjvXbK+9Lhsm1b21k=",
    "VersionHash": "rEZ2fTASmOCBw6yzUmHCywv8QGY="
  },
  "64,-38": {
    "SourceVersionHash": "o1yIP49yThqcdwiyziuGPD6ICOE=",
    "VersionHash": "rEZ2fTASmOCBw6yzUmHCywv8QGY="
  },
  "64,-35": {
    "SourceVersionHash": "o1yIP49yThqcdwiyziuGPD6ICOE=",
    "VersionHash": "rEZ2fTASmOCBw6yzUmHCywv8QGY="
  },
  "66,-40": {
    "SourceVersionHash": "o1yIP49yThqcdwiyziuGPD6ICOE=",
    "VersionHash": "viyHSlgBplXbs793wGh/zfYoRXA="
  },
  "65,-40": {
    "SourceVersionHash": "o1yIP49yThqcdwiyziuGPD6ICOE=",
    "VersionHash": "viyHSlgBplXbs793wGh/zfYoRXA="
  },
  "63,-33": {
    "SourceVersionHash": "3ssxTk9I94yjvXbK+9Lhsm1b21k=",
    "VersionHash": "rEZ2fTASmOCBw6yzUmHCywv8QGY="
  },
  "66,-32": {
    "SourceVersionHash": "oM9pNtQh72w3g6sBjbbIa1530qM=",
    "VersionHash": "7JAO6Fy3HuPTL88uoc8wMDSRJMA="
  },
  "69,-33": {
    "SourceVersionHash": "o1yIP49yThqcdwiyziuGPD6ICOE=",
    "VersionHash": "viyHSlgBplXbs793wGh/zfYoRXA="
  },
  "65,-39": {
    "SourceVersionHash": "o1yIP49yThqcdwiyziuGPD6ICOE=",
    "VersionHash": "lJKo50H+lCe+QbHNaxkDz1wEX0w="
  },
  "64,-36": {
    "SourceVersionHash": "o1yIP49yThqcdwiyziuGPD6ICOE=",
    "VersionHash": "rEZ2fTASmOCBw6yzUmHCywv8QGY="
  },
  "64,-40": {
    "SourceVersionHash": "o1yIP49yThqcdwiyziuGPD6ICOE=",
    "VersionHash": "rEZ2fTASmOCBw6yzUmHCywv8QGY="
  },
  "66,-33": {
    "SourceVersionHash": "o1yIP49yThqcdwiyziuGPD6ICOE=",
    "VersionHash": "viyHSlgBplXbs793wGh/zfYoRXA="
  },
  "65,-33": {
    "SourceVersionHash": "o1yIP49yThqcdwiyziuGPD6ICOE=",
    "VersionHash": "viyHSlgBplXbs793wGh/zfYoRXA="
  },
  "68,-34": {
    "SourceVersionHash": "o1yIP49yThqcdwiyziuGPD6ICOE=",
    "VersionHash": "lJKo50H+lCe+QbHNaxkDz1wEX0w="
  },
  "68,-33": {
    "SourceVersionHash": "o1yIP49yThqcdwiyziuGPD6ICOE=",
    "VersionHash": "viyHSlgBplXbs793wGh/zfYoRXA="
  },
  "68,-35": {
    "SourceVersionHash": "o1yIP49yThqcdwiyziuGPD6ICOE=",
    "VersionHash": "lJKo50H+lCe+QbHNaxkDz1wEX0w="
  },
  "66,-37": {
    "SourceVersionHash": "o1yIP49yThqcdwiyziuGPD6ICOE=",
    "VersionHash": "lJKo50H+lCe+QbHNaxkDz1wEX0w="
  },
  "65,-34": {
    "SourceVersionHash": "o1yIP49yThqcdwiyziuGPD6ICOE=",
    "VersionHash": "lJKo50H+lCe+QbHNaxkDz1wEX0w="
  },
  "63,-40": {
    "SourceVersionHash": "3ssxTk9I94yjvXbK+9Lhsm1b21k=",
    "VersionHash": "rEZ2fTASmOCBw6yzUmHCywv8QGY="
  },
  "67,-40": {
    "SourceVersionHash": "o1yIP49yThqcdwiyziuGPD6ICOE=",
    "VersionHash": "viyHSlgBplXbs793wGh/zfYoRXA="
  },
  "69,-40": {
    "SourceVersionHash": "o1yIP49yThqcdwiyziuGPD6ICOE=",
    "VersionHash": "viyHSlgBplXbs793wGh/zfYoRXA="
  },
  "67,-33": {
    "SourceVersionHash": "o1yIP49yThqcdwiyziuGPD6ICOE=",
    "VersionHash": "viyHSlgBplXbs793wGh/zfYoRXA="
  },
  "64,-39": {
    "SourceVersionHash": "o1yIP49yThqcdwiyziuGPD6ICOE=",
    "VersionHash": "rEZ2fTASmOCBw6yzUmHCywv8QGY="
  },
  "68,-37": {
    "SourceVersionHash": "o1yIP49yThqcdwiyziuGPD6ICOE=",
    "VersionHash": "lJKo50H+lCe+QbHNaxkDz1wEX0w="
  },
  "63,-39": {
    "SourceVersionHash": "3ssxTk9I94yjvXbK+9Lhsm1b21k=",
    "VersionHash": "rEZ2fTASmOCBw6yzUmHCywv8QGY="
  },
  "66,-39": {
    "SourceVersionHash": "o1yIP49yThqcdwiyziuGPD6ICOE=",
    "VersionHash": "lJKo50H+lCe+QbHNaxkDz1wEX0w="
  },
  "68,-39": {
    "SourceVersionHash": "o1yIP49yThqcdwiyziuGPD6ICOE=",
    "VersionHash": "lJKo50H+lCe+QbHNaxkDz1wEX0w="
  },
  "67,-39": {
    "SourceVersionHash": "o1yIP49yThqcdwiyziuGPD6ICOE=",
    "VersionHash": "lJKo50H+lCe+QbHNaxkDz1wEX0w="
  },
  "65,-36": {
    "SourceVersionHash": "o1yIP49yThqcdwiyziuGPD6ICOE=",
    "VersionHash": "lJKo50H+lCe+QbHNaxkDz1wEX0w="
  },
  "65,-37": {
    "SourceVersionHash": "o1yIP49yThqcdwiyziuGPD6ICOE=",
    "VersionHash": "lJKo50H+lCe+QbHNaxkDz1wEX0w="
  },
  "67,-32": {
    "SourceVersionHash": "oM9pNtQh72w3g6sBjbbIa1530qM=",
    "VersionHash": "7JAO6Fy3HuPTL88uoc8wMDSRJMA="
  },
  "68,-36": {
    "SourceVersionHash": "o1yIP49yThqcdwiyziuGPD6ICOE=",
    "VersionHash": "lJKo50H+lCe+QbHNaxkDz1wEX0w="
  },
  "69,-39": {
    "SourceVersionHash": "o1yIP49yThqcdwiyziuGPD6ICOE=",
    "VersionHash": "lJKo50H+lCe+QbHNaxkDz1wEX0w="
  }
}